[{
    "modulo": "Choferes",
    "data": [{
            "name": "Listado",
            "controller": "Choferes",
            "slug": "drivers.index"
        },
        {
            "name": "Crear",
            "controller": "Choferes",
            "slug": "drivers.create"
        },
        {
            "name": "Guardar",
            "controller": "Choferes",
            "slug": "drivers.store"
        },
        {
            "name": "Visualizar",
            "controller": "Choferes",
            "slug": "drivers.show"
        },
        {
            "name": "Editar",
            "controller": "Choferes",
            "slug": "drivers.edit"
        },
        {
            "name": "Actualizar",
            "controller": "Choferes",
            "slug": "drivers.update"
        },
        {
            "name": "Borrar",
            "controller": "Choferes",
            "slug": "drivers.destroy"
        },
        {
            "name": "Estatus",
            "controller": "Choferes",
            "slug": "drivers.status"
        }
    ]
}]
